marl_neon_grid/__init__.py
marl_neon_grid/ray_caster.py
marl_neon_grid/commands/__init__.py
marl_neon_grid/commands/command.py
marl_neon_grid/commands/eat_food_command.py
marl_neon_grid/commands/movement_commands.py
marl_neon_grid/commands/open_door_command.py
marl_neon_grid/entitites/__init__.py
marl_neon_grid/entitites/agent.py
marl_neon_grid/entitites/door.py
marl_neon_grid/entitites/entity.py
marl_neon_grid/entitites/floor.py
marl_neon_grid/entitites/food.py
marl_neon_grid/entitites/states.py
marl_neon_grid/entitites/wall.py
marl_neon_grid/entitites/zone.py
marl_neon_grid/environments/__init__.py
marl_neon_grid/environments/gridworld.py
marl_neon_grid/environments/closed_rooms/__init__.py
marl_neon_grid/environments/closed_rooms/closed_rooms.py
marl_neon_grid/environments/closed_rooms/game_state.py
marl_neon_grid/environments/closed_rooms/levels/10x10_left.txt
marl_neon_grid/environments/closed_rooms/levels/10x10_right.txt
marl_neon_grid/environments/doors_n_agents/__init__.py
marl_neon_grid/environments/doors_n_agents/doors_n_agents.py
marl_neon_grid/environments/doors_n_agents/levels/10x10_2A.txt
marl_neon_grid/environments/doors_n_agents/levels/10x10_2A_hard.txt
marl_neon_grid/environments/food_n_agents/__init__.py
marl_neon_grid/environments/food_n_agents/food_n_agents.py
marl_neon_grid/environments/food_n_agents/game_state.py
marl_neon_grid/environments/food_n_agents/levels/10x10.txt
marl_neon_grid/rendering/__init__.py
marl_neon_grid/rendering/base_renderer.py
marl_neon_grid/rendering/render_groups.py
marl_neon_grid/rendering/renderer.py
marl_neon_grid/rendering/assets/drop_off.png
marl_neon_grid/rendering/assets/food.png
marl_neon_grid/rendering/assets/item.png
marl_neon_grid/rendering/assets/logo.png
marl_neon_grid/rendering/assets/zone.png
marl_neon_grid/rendering/assets/agents/adversary.png
marl_neon_grid/rendering/assets/agents/agent.png
marl_neon_grid/rendering/assets/agents/agent_collision.png
Marl_Neon_Grid-0.1.4.5.dist-info/LICENSE
Marl_Neon_Grid-0.1.4.5.dist-info/METADATA
Marl_Neon_Grid-0.1.4.5.dist-info/WHEEL
Marl_Neon_Grid-0.1.4.5.dist-info/top_level.txt
Marl_Neon_Grid-0.1.4.5.dist-info/RECORD
