Metadata-Version: 2.1
Name: Marl-Neon-Grid
Version: 0.1.4.5
Summary: A collection of MARL gridworlds to study coordination and cooperation.
Home-page: https://github.com/romue404/marl-neon-grid
Author: Robert Müller
Author-email: robert.mueller1990@googlemail.com
License: MIT
Keywords: artificial intelligence,pytorch,multiagent reinforcement learning,simulation
Classifier: Development Status :: 4 - Beta
Classifier: Intended Audience :: Developers
Classifier: Topic :: Scientific/Engineering :: Artificial Intelligence
Classifier: License :: OSI Approved :: MIT License
Classifier: Programming Language :: Python :: 3.6
License-File: LICENSE
Requires-Dist: numpy
Requires-Dist: pygame >=2.0
Requires-Dist: numba >=0.56
Requires-Dist: gymnasium >=0.26
